app/__init__.py
app/cli.py
app/config.py
app/extensions.py
app/models.py
app/utils.py
app/auth/__init__.py
app/auth/routes.py
app/auth/schemas.py
app/auth/utils.py
app/main/__init__.py
app/main/routes.py
app/main/schemas.py
app/products/__init__.py
app/products/routes.py
app/services/__init__.py
app/services/email.py
app/users/__init__.py
app/users/routes.py
tests/__init__.py
tests/test_auth.py
tests/test_main.py
gisflask-0.1.4.dist-info/METADATA
gisflask-0.1.4.dist-info/WHEEL
gisflask-0.1.4.dist-info/entry_points.txt
gisflask-0.1.4.dist-info/top_level.txt
gisflask-0.1.4.dist-info/RECORD
