Metadata-Version: 2.4
Name: gisflask
Version: 0.1.4
Summary: A Flask-based GIS backend package
Home-page: https://github.com/KimutaiLawrence/gisflask
Author: Lawrence Kimutai
Author-email: lawrencekimutai001@gmail.com
Classifier: Development Status :: 3 - Alpha
Classifier: Intended Audience :: Developers
Classifier: License :: OSI Approved :: MIT License
Classifier: Programming Language :: Python :: 3
Classifier: Programming Language :: Python :: 3.9
Classifier: Programming Language :: Python :: 3.10
Classifier: Programming Language :: Python :: 3.11
Classifier: Topic :: Scientific/Engineering :: GIS
Classifier: Framework :: Flask
Requires-Python: >=3.9
Requires-Dist: Flask>=2.0.0
Requires-Dist: Flask-SQLAlchemy>=3.0.0
Requires-Dist: Flask-Login>=0.6.0
Requires-Dist: Flask-WTF>=1.0.0
Requires-Dist: SQLAlchemy>=2.0.0
Requires-Dist: Werkzeug>=2.0.0
Requires-Dist: email-validator>=1.0.0
Requires-Dist: python-dotenv>=0.19.0
Requires-Dist: folium>=0.12.0
Requires-Dist: geopandas>=0.10.0
Requires-Dist: shapely>=1.8.0
Requires-Dist: geopy>=2.2.0
Requires-Dist: pandas>=1.3.0
Requires-Dist: numpy>=1.21.0
Requires-Dist: requests>=2.26.0
Requires-Dist: gunicorn>=20.1.0
Requires-Dist: psycopg2-binary>=2.9.0
Requires-Dist: alembic>=1.7.0
Requires-Dist: pytest>=6.2.0
Requires-Dist: pytest-cov>=2.12.0
Requires-Dist: black>=21.5b2
Requires-Dist: flake8>=3.9.0
Requires-Dist: mypy>=0.910
Requires-Dist: isort>=5.9.0
Requires-Dist: pre-commit>=2.15.0
Requires-Dist: sphinx>=4.0.0
Requires-Dist: sphinx-rtd-theme>=0.5.0
Requires-Dist: twine>=3.4.0
Requires-Dist: wheel>=0.37.0
Requires-Dist: build>=0.7.0
Provides-Extra: dev
Requires-Dist: pytest>=6.2.0; extra == "dev"
Requires-Dist: pytest-cov>=2.12.0; extra == "dev"
Requires-Dist: black>=21.5b2; extra == "dev"
Requires-Dist: flake8>=3.9.0; extra == "dev"
Requires-Dist: mypy>=0.910; extra == "dev"
Requires-Dist: isort>=5.9.0; extra == "dev"
Requires-Dist: pre-commit>=2.15.0; extra == "dev"
Requires-Dist: sphinx>=4.0.0; extra == "dev"
Requires-Dist: sphinx-rtd-theme>=0.5.0; extra == "dev"
Requires-Dist: twine>=3.4.0; extra == "dev"
Requires-Dist: wheel>=0.37.0; extra == "dev"
Requires-Dist: build>=0.7.0; extra == "dev"
Dynamic: author
Dynamic: author-email
Dynamic: classifier
Dynamic: description
Dynamic: description-content-type
Dynamic: home-page
Dynamic: provides-extra
Dynamic: requires-dist
Dynamic: requires-python
Dynamic: summary
